distsrclient/__init__.py
distsrclient-0.0.0.dist-info/METADATA
distsrclient-0.0.0.dist-info/WHEEL
distsrclient-0.0.0.dist-info/licenses/LICENSE
distsrclient-0.0.0.dist-info/RECORD
