Metadata-Version: 2.1
Name: distsrclient
Version: 0.0.0
Summary: distributed send socket and receive socket client.
Project-URL: Homepage, https://github.com/chorong8883/distsrclient
Author-email: Chor <chorong8883@gmail.com>
License-File: LICENSE
Keywords: client,distribute,distsrclient,socket
Classifier: License :: OSI Approved :: MIT License
Classifier: Operating System :: MacOS
Classifier: Operating System :: POSIX :: Linux
Classifier: Programming Language :: Python :: 3.10
Requires-Python: >=3.10
